python_packaging_flit_wise/__init__.py
python_packaging_flit_wise/http.py
python_packaging_flit_wise/searcher.py
python_packaging_flit_wise-0.3.1.dist-info/LICENSE
python_packaging_flit_wise-0.3.1.dist-info/WHEEL
python_packaging_flit_wise-0.3.1.dist-info/METADATA
python_packaging_flit_wise-0.3.1.dist-info/RECORD
