Metadata-Version: 2.1
Name: python_packaging_flit_wise
Version: 0.3.1
Summary: Let's find some podcasts!
Home-page: https://github.com/wisemuffin/python_packaging_flit_wise-py
Author: wisemuffin
Author-email: davidgg777@hotmail.com
Requires-Python: >=3.7
Classifier: License :: OSI Approved :: MIT License
